halmos/__init__.py
halmos/__main__.py
halmos/assertions.py
halmos/bitvec.py
halmos/build.py
halmos/bytevec.py
halmos/calldata.py
halmos/cheatcodes.py
halmos/config.py
halmos/console.py
halmos/constants.py
halmos/contract.py
halmos/env.py
halmos/exceptions.py
halmos/flamegraphs.py
halmos/hashes.py
halmos/logs.py
halmos/mapper.py
halmos/memtrace.py
halmos/processes.py
halmos/sevm.py
halmos/solve.py
halmos/solvers.py
halmos/traces.py
halmos/ui.py
halmos/utils.py
halmos-0.3.3.dist-info/licenses/LICENSE
halmos-0.3.3.dist-info/METADATA
halmos-0.3.3.dist-info/WHEEL
halmos-0.3.3.dist-info/entry_points.txt
halmos-0.3.3.dist-info/top_level.txt
halmos-0.3.3.dist-info/RECORD
