Metadata-Version: 2.4
Name: halmos
Version: 0.3.3
Summary: A symbolic testing tool for EVM smart contracts
Author: a16z crypto
Maintainer: Daejun Park, karmacoma <karma@coma.lol>
Project-URL: Homepage, https://github.com/a16z/halmos
Classifier: Programming Language :: Python :: 3
Classifier: License :: OSI Approved :: GNU Affero General Public License v3
Classifier: Operating System :: OS Independent
Requires-Python: >=3.11
License-File: LICENSE
Requires-Dist: sortedcontainers>=2.4.0
Requires-Dist: toml>=0.10.2
Requires-Dist: z3-solver==4.12.6.0
Requires-Dist: eth_hash[pysha3]>=0.7.0
Requires-Dist: rich<14.1.0,>=14.0.0
Requires-Dist: xxhash>=3.5.0
Requires-Dist: psutil>=6.1.0
Requires-Dist: requests>=2.32.3
Requires-Dist: yices-solver<2.6.5,>=2.6.4
Requires-Dist: python-dotenv>=1.1.0
Provides-Extra: dev
Requires-Dist: pre-commit>=4.0.1; extra == "dev"
Requires-Dist: pytest>=8.3.4; extra == "dev"
Requires-Dist: ruff>=0.8.1; extra == "dev"
Dynamic: license-file
